crypto_market_wrapper/__init__.py
crypto_market_wrapper/crypto.py
crypto_market_wrapper-0.4.0.dist-info/WHEEL
crypto_market_wrapper-0.4.0.dist-info/METADATA
crypto_market_wrapper-0.4.0.dist-info/RECORD
