Metadata-Version: 2.1
Name: crypto-market-wrapper
Version: 0.4.0
Summary: 
Home-page: https://github.com/hasindusithmin/crypto-market-wrapper.git
Author: hasindusithmin
Author-email: hasindusithmin64@gmail.com
Requires-Python: >=3.6,<4.0
Classifier: Programming Language :: Python :: 3
Classifier: Programming Language :: Python :: 3.10
Classifier: Programming Language :: Python :: 3.6
Classifier: Programming Language :: Python :: 3.7
Classifier: Programming Language :: Python :: 3.8
Classifier: Programming Language :: Python :: 3.9
Requires-Dist: pandas (>=1.5.2,<2.0.0)
Requires-Dist: requests (>=2.28.1,<3.0.0)
Project-URL: Repository, https://github.com/hasindusithmin/crypto-market-wrapper.git
